sfai/__init__.py
sfai/_version.py
sfai/constants.py
sfai/main.py
sfai/app/__init__.py
sfai/app/context.py
sfai/app/delete.py
sfai/app/deploy.py
sfai/app/helm.py
sfai/app/init.py
sfai/app/logs.py
sfai/app/open.py
sfai/app/publish.py
sfai/app/status.py
sfai/app/utils/helpers.py
sfai/app/utils/scaffold.py
sfai/cli/__init__.py
sfai/cli/app/__init__.py
sfai/cli/app/context.py
sfai/cli/app/delete.py
sfai/cli/app/deploy.py
sfai/cli/app/helm.py
sfai/cli/app/init.py
sfai/cli/app/logs.py
sfai/cli/app/open.py
sfai/cli/app/publish.py
sfai/cli/app/status.py
sfai/cli/config/__init__.py
sfai/cli/config/delete.py
sfai/cli/config/init.py
sfai/cli/config/list.py
sfai/cli/config/update.py
sfai/cli/config/view.py
sfai/cli/platform/__init__.py
sfai/cli/platform/init.py
sfai/cli/platform/switch.py
sfai/config/__init__.py
sfai/config/delete.py
sfai/config/init.py
sfai/config/list.py
sfai/config/registry.py
sfai/config/update.py
sfai/config/view.py
sfai/config/schemas/mulesoft.py
sfai/config/utils/validate.py
sfai/context/__init__.py
sfai/context/manager.py
sfai/context/models.py
sfai/core/__init__.py
sfai/core/base.py
sfai/core/decorators.py
sfai/core/response_models.py
sfai/core/agentforce/__init__.py
sfai/core/agentforce/decorators.py
sfai/core/agentforce/generator.py
sfai/core/agentforce/helper.py
sfai/core/templates/fastapi_hello/Dockerfile
sfai/core/templates/fastapi_hello/Procfile
sfai/core/templates/fastapi_hello/app.py
sfai/core/templates/fastapi_hello/requirements.txt
sfai/core/templates/fastapi_hello/version.json
sfai/integrations/__init__.py
sfai/integrations/registry.py
sfai/integrations/mulesoft/agentforce_utils.py
sfai/integrations/mulesoft/core.py
sfai/integrations/mulesoft/publish.py
sfai/integrations/mulesoft/publish_cli.py
sfai/integrations/mulesoft/utils.py
sfai/platform/__init__.py
sfai/platform/init.py
sfai/platform/registry.py
sfai/platform/switch.py
sfai/platform/providers/eks/__init__.py
sfai/platform/providers/eks/platform.py
sfai_sdk-0.14b0.dist-info/licenses/LICENSE.txt
sfai_sdk-0.14b0.dist-info/METADATA
sfai_sdk-0.14b0.dist-info/WHEEL
sfai_sdk-0.14b0.dist-info/entry_points.txt
sfai_sdk-0.14b0.dist-info/top_level.txt
sfai_sdk-0.14b0.dist-info/RECORD
