Metadata-Version: 2.4
Name: sfai-sdk
Version: 0.14b0
Summary: A zero-config Python CLI to scaffold, containerize, and deploy FastAPI apps
Author-email: Jaswanth Rao Billakanti <jbillakanti@salesforce.com>
Classifier: Development Status :: 4 - Beta
Classifier: Operating System :: Unix
Classifier: Programming Language :: Python
Classifier: Programming Language :: Python :: 3
Classifier: Programming Language :: Python :: 3.10
Classifier: Programming Language :: Python :: 3.11
Classifier: Programming Language :: Python :: 3.12
Requires-Python: >=3.9
License-File: LICENSE.txt
Requires-Dist: typer>=0.9.0
Requires-Dist: rich>=13.7.1
Requires-Dist: pydantic>=2.0.0
Requires-Dist: PyYAML>=6.0
Requires-Dist: click>=8.1.7
Requires-Dist: boto3>=1.24.0
Requires-Dist: kubernetes>=27.2.0
Requires-Dist: termcolor>=2.0.0
Requires-Dist: requests
Requires-Dist: fastapi>=0.100.0
Provides-Extra: dev
Requires-Dist: build; extra == "dev"
Requires-Dist: pre-commit; extra == "dev"
Requires-Dist: pytest>=7.0.0; extra == "dev"
Requires-Dist: pytest-cov>=4.0.0; extra == "dev"
Requires-Dist: mypy; extra == "dev"
Requires-Dist: pytest-html; extra == "dev"
Requires-Dist: pytest-xdist; extra == "dev"
Requires-Dist: black; extra == "dev"
Requires-Dist: isort; extra == "dev"
Requires-Dist: ruff; extra == "dev"
Requires-Dist: absolufy-imports>=0.3.1; extra == "dev"
Requires-Dist: pytest-mock>=3.10.0; extra == "dev"
Requires-Dist: nbstripout>=0.6.0; extra == "dev"
Provides-Extra: docs
Requires-Dist: mkdocs>=1.5.0; extra == "docs"
Requires-Dist: mkdocs-material>=9.0.0; extra == "docs"
Requires-Dist: mkdocs-jupyter>=0.24.0; extra == "docs"
Requires-Dist: mkdocstrings[python]>=0.22.0; extra == "docs"
Requires-Dist: mkdocs-git-authors-plugin>=0.7.0; extra == "docs"
Requires-Dist: mkdocs-git-revision-date-localized-plugin>=1.2.0; extra == "docs"
Requires-Dist: pymdown-extensions>=10.0.0; extra == "docs"
Provides-Extra: all
Requires-Dist: sfai[dev,docs]; extra == "all"
Dynamic: license-file
